thermoparsec/lib/componentdetection/cdl.py
thermoparsec/lib/componentdetection/pcore.py
thermoparsec/lib/componentdetection/pdata.py
thermoparsec/lib/librarysearching/ConvexSearch.py
thermoparsec/lib/librarysearching/MerlinHT.py
thermoparsec/lib/scratch/CD.py
thermoparsec/lib/scratch/CDR.py
thermoparsec/lib/scratch/PPD.py
thermoparsec-2.3.4.dist-info/DESCRIPTION.rst
thermoparsec-2.3.4.dist-info/METADATA
thermoparsec-2.3.4.dist-info/RECORD
thermoparsec-2.3.4.dist-info/WHEEL
thermoparsec-2.3.4.dist-info/metadata.json
thermoparsec-2.3.4.dist-info/top_level.txt
