Metadata-Version: 2.0
Name: thermoparsec
Version: 2.3.4
Summary: Parsec Library
Home-page: UNKNOWN
Author: Iman Mohtashemi
Author-email: iman.mohtashemi@thermofisher.com
License: UNKNOWN
Keywords: thermoparsec
Platform: UNKNOWN
Classifier: Programming Language :: Python :: 2.7
